[{"salary":"18500","faculty":"วิศวกรรมเครื่องกล","company":"Mitsubishi Motor","year":"2559"},{"salary":"18500","faculty":"วิศวกรรมเครื่องกล","company":"Mitsubishi Motor","year":"2560"},{"salary":"18500","faculty":"วิศวกรรมเครื่องกล","company":"Mitsubishi Motor","year":"2561"},{"salary":"18500","faculty":"วิศวกรรมเครื่องกล","company":"Mitsubishi Motor","year":"2562"},{"salary":"20000","faculty":"วิศวกรรมเครื่องกล","company":"Toyota Motor","year":"2559"},{"salary":"20000","faculty":"วิศวกรรมเครื่องกล","company":"Toyota Motor","year":"2560"},{"salary":"20500","faculty":"วิศวกรรมเครื่องกล","company":"Toyota Motor","year":"2561"},{"salary":"20500","faculty":"วิศวกรรมเครื่องกล","company":"Toyota Motor","year":"2562"},{"salary":"19500","faculty":"วิศวกรรมเครื่องกล","company":"Isuzu Motor","year":"2559"},{"salary":"20000","faculty":"วิศวกรรมเครื่องกล","company":"Isuzu Motor","year":"2560"},{"salary":"20000","faculty":"วิศวกรรมเครื่องกล","company":"Isuzu Motor","year":"2561"},{"salary":"20000","faculty":"วิศวกรรมเครื่องกล","company":"Isuzu Motor","year":"2562"},{"salary":"19500","faculty":"วิศวกรรมเครื่องกล","company":"Honda Motor","year":"2559"},{"salary":"19500","faculty":"วิศวกรรมเครื่องกล","company":"Honda Motor","year":"2560"},{"salary":"20000","faculty":"วิศวกรรมเครื่องกล","company":"Honda Motor","year":"2561"},{"salary":"20000","faculty":"วิศวกรรมเครื่องกล","company":"Honda Motor","year":"2562"},{"salary":"18500","faculty":"วิศวกรรมเครื่องกล","company":"NISSAN Motor","year":"2559"},{"salary":"18500","faculty":"วิศวกรรมเครื่องกล","company":"NISSAN Motor","year":"2560"},{"salary":"18500","faculty":"วิศวกรรมเครื่องกล","company":"NISSAN Motor","year":"2561"},{"salary":"18500","faculty":"วิศวกรรมเครื่องกล","company":"NISSAN Motor","year":"2562"},{"salary":"15000","faculty":"วิศวกรรมโยธา","company":"อิตาเลียนไทย","year":"2559"},{"salary":"15000","faculty":"วิศวกรรมโยธา","company":"อิตาเลียนไทย","year":"2560"},{"salary":"15000","faculty":"วิศวกรรมโยธา","company":"อิตาเลียนไทย","year":"2561"},{"salary":"15000","faculty":"วิศวกรรมโยธา","company":"อิตาเลียนไทย","year":"2562"},{"salary":"13000","faculty":"วิศวกรรมโยธา","company":"Takenaka","year":"2559"},{"salary":"13000","faculty":"วิศวกรรมโยธา","company":"Takenaka","year":"2560"},{"salary":"13000","faculty":"วิศวกรรมโยธา","company":"Takenaka","year":"2561"},{"salary":"13000","faculty":"วิศวกรรมโยธา","company":"Takenaka","year":"2562"},{"salary":"15000","faculty":"วิศวกรรมโยธา","company":"พฤกษา","year":"2559"},{"salary":"","faculty":"วิศวกรรมโยธา","company":"พฤกษา","year":"2560"},{"salary":"15000","faculty":"วิศวกรรมโยธา","company":"พฤกษา","year":"2561"},{"salary":"15000","faculty":"วิศวกรรมโยธา","company":"พฤกษา","year":"2562"},{"salary":"20000","faculty":"การบริหารจัดการ","company":"thai samsung","year":"2559"},{"salary":"20000","faculty":"การบริหารจัดการ","company":"thai samsung","year":"2560"},{"salary":"","faculty":"การบริหารจัดการ","company":"thai samsung","year":"2561"},{"salary":"20000","faculty":"การบริหารจัดการ","company":"thai samsung","year":"2562"},{"salary":"","faculty":"วิศวกรรมไฟฟ้า","company":"DAIKIN INDUSTRY","year":"2559"},{"salary":"","faculty":"วิศวกรรมไฟฟ้า","company":"DAIKIN INDUSTRY","year":"2560"},{"salary":"18500","faculty":"วิศวกรรมไฟฟ้า","company":"DAIKIN INDUSTRY","year":"2561"},{"salary":"18500","faculty":"วิศวกรรมไฟฟ้า","company":"DAIKIN INDUSTRY","year":"2562"},{"salary":"","faculty":"วิศวกรรมไฟฟ้า","company":"THAI SAMSUNG ELECTRONIC","year":"2559"},{"salary":"19100","faculty":"วิศวกรรมไฟฟ้า","company":"THAI SAMSUNG ELECTRONIC","year":"2560"},{"salary":"19100","faculty":"วิศวกรรมไฟฟ้า","company":"THAI SAMSUNG ELECTRONIC","year":"2561"},{"salary":"19100","faculty":"วิศวกรรมไฟฟ้า","company":"THAI SAMSUNG ELECTRONIC","year":"2562"},{"salary":"","faculty":"วิศวกรรมอาหาร","company":"Duth Milk","year":"2559"},{"salary":"","faculty":"วิศวกรรมอาหาร","company":"Duth Milk","year":"2560"},{"salary":"","faculty":"วิศวกรรมอาหาร","company":"Duth Milk","year":"2561"},{"salary":"23000","faculty":"วิศวกรรมอาหาร","company":"Duth Milk","year":"2562"},{"salary":"","faculty":"วิศวกรรมเคมี","company":"SCG Chemical","year":"2559"},{"salary":"","faculty":"วิศวกรรมเคมี","company":"SCG Chemical","year":"2560"},{"salary":"38500","faculty":"วิศวกรรมเคมี","company":"SCG Chemical","year":"2561"},{"salary":"38500","faculty":"วิศวกรรมเคมี","company":"SCG Chemical","year":"2562"},{"salary":"35000","faculty":"วิศวกรรมเคมี","company":"ThaiOil","year":"2559"},{"salary":"35000","faculty":"วิศวกรรมเคมี","company":"ThaiOil","year":"2560"},{"salary":"35000","faculty":"วิศวกรรมเคมี","company":"ThaiOil","year":"2561"},{"salary":"35000","faculty":"วิศวกรรมเคมี","company":"ThaiOil","year":"2562"},{"salary":"","faculty":"วิทยาการคอมพิวเตอร์","company":"ธนาคารกรุงเทพ จำกัด (มหาชน)","year":"2559"},{"salary":"","faculty":"วิทยาการคอมพิวเตอร์","company":"ธนาคารกรุงเทพ จำกัด (มหาชน)","year":"2560"},{"salary":"15000","faculty":"วิทยาการคอมพิวเตอร์","company":"ธนาคารกรุงเทพ จำกัด (มหาชน)","year":"2561"},{"salary":"15000","faculty":"วิทยาการคอมพิวเตอร์","company":"ธนาคารกรุงเทพ จำกัด (มหาชน)","year":"2562"},{"salary":"","faculty":"วิทยาการคอมพิวเตอร์","company":"AIS (Network Operations Center)","year":"2559"},{"salary":"","faculty":"วิทยาการคอมพิวเตอร์","company":"AIS (Network Operations Center)","year":"2560"},{"salary":"15000","faculty":"วิทยาการคอมพิวเตอร์","company":"AIS (Network Operations Center)","year":"2561"},{"salary":"15000","faculty":"วิทยาการคอมพิวเตอร์","company":"AIS (Network Operations Center)","year":"2562"},{"salary":"","faculty":"วิศวกรรมคอมพิวเตอร์","company":"AIS (Network Operations Center)","year":"2559"},{"salary":"","faculty":"วิศวกรรมคอมพิวเตอร์","company":"AIS (Network Operations Center)","year":"2560"},{"salary":"15000","faculty":"วิศวกรรมคอมพิวเตอร์","company":"AIS (Network Operations Center)","year":"2561"},{"salary":"15000","faculty":"วิศวกรรมคอมพิวเตอร์","company":"AIS (Network Operations Center)","year":"2562"},{"salary":"","faculty":"การบริหารจัดการ","company":"AIS (Marketing Support)","year":"2559"},{"salary":"","faculty":"การบริหารจัดการ","company":"AIS (Marketing Support)","year":"2560"},{"salary":"","faculty":"การบริหารจัดการ","company":"AIS (Marketing Support)","year":"2561"},{"salary":"15000","faculty":"การบริหารจัดการ","company":"AIS (Marketing Support)","year":"2562"},{"salary":"","faculty":"วิศวกรรมโทรคมนาคม","company":"True (Digital Representative)","year":"2559"},{"salary":"","faculty":"วิศวกรรมโทรคมนาคม","company":"True (Digital Representative)","year":"2560"},{"salary":"23000","faculty":"วิศวกรรมโทรคมนาคม","company":"True (Digital Representative)","year":"2561"},{"salary":"23000","faculty":"วิศวกรรมโทรคมนาคม","company":"True (Digital Representative)","year":"2562"},{"salary":"","faculty":"เทคโนโลยีสารสนเทศ","company":"Kerry Express (HRIS Support)","year":"2559"},{"salary":"","faculty":"เทคโนโลยีสารสนเทศ","company":"Kerry Express (HRIS Support)","year":"2560"},{"salary":"16000","faculty":"เทคโนโลยีสารสนเทศ","company":"Kerry Express (HRIS Support)","year":"2561"},{"salary":"16000","faculty":"เทคโนโลยีสารสนเทศ","company":"Kerry Express (HRIS Support)","year":"2562"},{"salary":"","faculty":"วิทยาการคอมพิวเตอร์","company":"3K Battery (VB.NET/ ASP.NET)","year":"2559"},{"salary":"","faculty":"วิทยาการคอมพิวเตอร์","company":"3K Battery (VB.NET/ ASP.NET)","year":"2560"},{"salary":"","faculty":"วิทยาการคอมพิวเตอร์","company":"3K Battery (VB.NET/ ASP.NET)","year":"2561"},{"salary":"15000","faculty":"วิทยาการคอมพิวเตอร์","company":"3K Battery (VB.NET/ ASP.NET)","year":"2562"},{"salary":"15000","faculty":"เกษตรศาสตร์","company":"Betagro (สัตวบาล ฟาร์มหมู)","year":"2559"},{"salary":"15000","faculty":"เกษตรศาสตร์","company":"Betagro (สัตวบาล ฟาร์มหมู)","year":"2560"},{"salary":"15000","faculty":"เกษตรศาสตร์","company":"Betagro (สัตวบาล ฟาร์มหมู)","year":"2561"},{"salary":"15000","faculty":"เกษตรศาสตร์","company":"Betagro (สัตวบาล ฟาร์มหมู)","year":"2562"},{"salary":"","faculty":"เกษตรศาสตร์","company":"makro (Operation Trainee-Fresh Food)","year":"2559"},{"salary":"","faculty":"เกษตรศาสตร์","company":"makro (Operation Trainee-Fresh Food)","year":"2560"},{"salary":"20000","faculty":"เกษตรศาสตร์","company":"makro (Operation Trainee-Fresh Food)","year":"2561"},{"salary":"20000","faculty":"เกษตรศาสตร์","company":"makro (Operation Trainee-Fresh Food)","year":"2562"},{"salary":"","faculty":"เทคโนโลยีสารสนเทศ","company":"Fujitsu (IT Service Desk)","year":"2559"},{"salary":"","faculty":"เทคโนโลยีสารสนเทศ","company":"Fujitsu (IT Service Desk)","year":"2560"},{"salary":"15000","faculty":"เทคโนโลยีสารสนเทศ","company":"Fujitsu (IT Service Desk)","year":"2561"},{"salary":"15000","faculty":"เทคโนโลยีสารสนเทศ","company":"Fujitsu (IT Service Desk)","year":"2562"},{"salary":"","faculty":"การบริหารจัดการ","company":"True(SPTD)","year":"2559"},{"salary":"","faculty":"การบริหารจัดการ","company":"True(SPTD)","year":"2560"},{"salary":"","faculty":"การบริหารจัดการ","company":"True(SPTD)","year":"2561"},{"salary":"22500","faculty":"การบริหารจัดการ","company":"True(SPTD)","year":"2562"},{"salary":"","faculty":"วิทยาการคอมพิวเตอร์","company":"บริษัท Microsoft","year":"2559"},{"salary":"","faculty":"วิทยาการคอมพิวเตอร์","company":"บริษัท Microsoft","year":"2560"},{"salary":"","faculty":"วิทยาการคอมพิวเตอร์","company":"บริษัท Microsoft","year":"2561"},{"salary":"20000","faculty":"วิทยาการคอมพิวเตอร์","company":"บริษัท Microsoft","year":"2562"},{"salary":"","faculty":"วิทยาการคอมพิวเตอร์","company":"บริษัท IBM Solution Delivery","year":"2559"},{"salary":"","faculty":"วิทยาการคอมพิวเตอร์","company":"บริษัท IBM Solution Delivery","year":"2560"},{"salary":"","faculty":"วิทยาการคอมพิวเตอร์","company":"บริษัท IBM Solution Delivery","year":"2561"},{"salary":"20000","faculty":"วิทยาการคอมพิวเตอร์","company":"บริษัท IBM Solution Delivery","year":"2562"},{"salary":"","faculty":"สถาปัตยกรรมภายใน","company":"Reeracoen Eastern Seaboard Recruitment Co., Ltd.","year":"2559"},{"salary":"","faculty":"สถาปัตยกรรมภายใน","company":"Reeracoen Eastern Seaboard Recruitment Co., Ltd.","year":"2560"},{"salary":"","faculty":"สถาปัตยกรรมภายใน","company":"Reeracoen Eastern Seaboard Recruitment Co., Ltd.","year":"2561"},{"salary":"20000","faculty":"สถาปัตยกรรมภายใน","company":"Reeracoen Eastern Seaboard Recruitment Co., Ltd.","year":"2562"},{"salary":"","faculty":"สถาปัตยกรรม","company":"VST DESIGN CO.,LTD","year":"2559"},{"salary":"","faculty":"สถาปัตยกรรม","company":"VST DESIGN CO.,LTD","year":"2560"},{"salary":"","faculty":"สถาปัตยกรรม","company":"VST DESIGN CO.,LTD","year":"2561"},{"salary":"20000","faculty":"สถาปัตยกรรม","company":"VST DESIGN CO.,LTD","year":"2562"},{"salary":"","faculty":"สถาปัตยกรรม","company":"บริษัท สยามดีไซน์ เฟอร์นิชิ่ง จำกัด","year":"2559"},{"salary":"","faculty":"สถาปัตยกรรม","company":"บริษัท สยามดีไซน์ เฟอร์นิชิ่ง จำกัด","year":"2560"},{"salary":"","faculty":"สถาปัตยกรรม","company":"บริษัท สยามดีไซน์ เฟอร์นิชิ่ง จำกัด","year":"2561"},{"salary":"20000","faculty":"สถาปัตยกรรม","company":"บริษัท สยามดีไซน์ เฟอร์นิชิ่ง จำกัด","year":"2562"},{"salary":"","faculty":"วิศวกรรมเครื่องกล","company":"Reeracoen Recruitment Co.,Ltd.","year":"2559"},{"salary":"","faculty":"วิศวกรรมเครื่องกล","company":"Reeracoen Recruitment Co.,Ltd.","year":"2560"},{"salary":"","faculty":"วิศวกรรมเครื่องกล","company":"Reeracoen Recruitment Co.,Ltd.","year":"2561"},{"salary":"18000","faculty":"วิศวกรรมเครื่องกล","company":"Reeracoen Recruitment Co.,Ltd.","year":"2562"},{"salary":"","faculty":"วิทยาการคอมพิวเตอร์","company":"TANGERINE CO., LTD.","year":"2559"},{"salary":"","faculty":"วิทยาการคอมพิวเตอร์","company":"TANGERINE CO., LTD.","year":"2560"},{"salary":"","faculty":"วิทยาการคอมพิวเตอร์","company":"TANGERINE CO., LTD.","year":"2561"},{"salary":"20000","faculty":"วิทยาการคอมพิวเตอร์","company":"TANGERINE CO., LTD.","year":"2562"},{"salary":"","faculty":"วิทยาการคอมพิวเตอร์","company":"SDL INC.","year":"2559"},{"salary":"","faculty":"วิทยาการคอมพิวเตอร์","company":"SDL INC.","year":"2560"},{"salary":"","faculty":"วิทยาการคอมพิวเตอร์","company":"SDL INC.","year":"2561"},{"salary":"20000","faculty":"วิทยาการคอมพิวเตอร์","company":"SDL INC.","year":"2562"},{"salary":"","faculty":"วิทยาการคอมพิวเตอร์","company":"Smartcruit Consultant Co., Ltd.","year":"2559"},{"salary":"","faculty":"วิทยาการคอมพิวเตอร์","company":"Smartcruit Consultant Co., Ltd.","year":"2560"},{"salary":"","faculty":"วิทยาการคอมพิวเตอร์","company":"Smartcruit Consultant Co., Ltd.","year":"2561"},{"salary":"20000","faculty":"วิทยาการคอมพิวเตอร์","company":"Smartcruit Consultant Co., Ltd.","year":"2562"},{"salary":"","faculty":"วิทยาการคอมพิวเตอร์","company":"CDG Group","year":"2559"},{"salary":"","faculty":"วิทยาการคอมพิวเตอร์","company":"CDG Group","year":"2560"},{"salary":"","faculty":"วิทยาการคอมพิวเตอร์","company":"CDG Group","year":"2561"},{"salary":"20000","faculty":"วิทยาการคอมพิวเตอร์","company":"CDG Group","year":"2562"},{"salary":"","faculty":"เกษตรศาสตร์","company":"Charoen Pokphand Foods Public Company Limited","year":"2559"},{"salary":"","faculty":"เกษตรศาสตร์","company":"Charoen Pokphand Foods Public Company Limited","year":"2560"},{"salary":"","faculty":"เกษตรศาสตร์","company":"Charoen Pokphand Foods Public Company Limited","year":"2561"},{"salary":"20000","faculty":"เกษตรศาสตร์","company":"Charoen Pokphand Foods Public Company Limited","year":"2562"},{"salary":"","faculty":"เทคโนโลยีสารสนเทศ","company":"Charoen Pokphand Foods Public Company Limited","year":"2559"},{"salary":"","faculty":"เทคโนโลยีสารสนเทศ","company":"Charoen Pokphand Foods Public Company Limited","year":"2560"},{"salary":"","faculty":"เทคโนโลยีสารสนเทศ","company":"Charoen Pokphand Foods Public Company Limited","year":"2561"},{"salary":"20000","faculty":"เทคโนโลยีสารสนเทศ","company":"Charoen Pokphand Foods Public Company Limited","year":"2562"},{"salary":"","faculty":"วิทยาการคอมพิวเตอร์","company":"Charoen Pokphand Foods Public Company Limited","year":"2559"},{"salary":"","faculty":"วิทยาการคอมพิวเตอร์","company":"Charoen Pokphand Foods Public Company Limited","year":"2560"},{"salary":"","faculty":"วิทยาการคอมพิวเตอร์","company":"Charoen Pokphand Foods Public Company Limited","year":"2561"},{"salary":"20000","faculty":"วิทยาการคอมพิวเตอร์","company":"Charoen Pokphand Foods Public Company Limited","year":"2562"},{"salary":"","faculty":"การบริหารจัดการ","company":"Charoen Pokphand Foods Public Company Limited","year":"2559"},{"salary":"","faculty":"การบริหารจัดการ","company":"Charoen Pokphand Foods Public Company Limited","year":"2560"},{"salary":"","faculty":"การบริหารจัดการ","company":"Charoen Pokphand Foods Public Company Limited","year":"2561"},{"salary":"20000","faculty":"การบริหารจัดการ","company":"Charoen Pokphand Foods Public Company Limited","year":"2562"},{"salary":"","faculty":"วิทยาการคอมพิวเตอร์","company":"PTT Digital Solutions Company Limited","year":"2559"},{"salary":"","faculty":"วิทยาการคอมพิวเตอร์","company":"PTT Digital Solutions Company Limited","year":"2560"},{"salary":"","faculty":"วิทยาการคอมพิวเตอร์","company":"PTT Digital Solutions Company Limited","year":"2561"},{"salary":"20000","faculty":"วิทยาการคอมพิวเตอร์","company":"PTT Digital Solutions Company Limited","year":"2562"},{"salary":"","faculty":"วิศวกรรมคอมพิวเตอร์","company":"PTT Digital Solutions Company Limited","year":"2559"},{"salary":"","faculty":"วิศวกรรมคอมพิวเตอร์","company":"PTT Digital Solutions Company Limited","year":"2560"},{"salary":"","faculty":"วิศวกรรมคอมพิวเตอร์","company":"PTT Digital Solutions Company Limited","year":"2561"},{"salary":"20000","faculty":"วิศวกรรมคอมพิวเตอร์","company":"PTT Digital Solutions Company Limited","year":"2562"},{"salary":"","faculty":"วิทยาการคอมพิวเตอร์","company":"Kaidee","year":"2559"},{"salary":"","faculty":"วิทยาการคอมพิวเตอร์","company":"Kaidee","year":"2560"},{"salary":"","faculty":"วิทยาการคอมพิวเตอร์","company":"Kaidee","year":"2561"},{"salary":"20000","faculty":"วิทยาการคอมพิวเตอร์","company":"Kaidee","year":"2562"},{"salary":"","faculty":"สถาปัตยกรรม","company":"KK Design Studio Architect Construction Co., Ltd.","year":"2559"},{"salary":"","faculty":"สถาปัตยกรรม","company":"KK Design Studio Architect Construction Co., Ltd.","year":"2560"},{"salary":"","faculty":"สถาปัตยกรรม","company":"KK Design Studio Architect Construction Co., Ltd.","year":"2561"},{"salary":"30000","faculty":"สถาปัตยกรรม","company":"KK Design Studio Architect Construction Co., Ltd.","year":"2562"},{"salary":"","faculty":"วิศวกรรมโยธา","company":"SGS (Thailand) Limited","year":"2559"},{"salary":"","faculty":"วิศวกรรมโยธา","company":"SGS (Thailand) Limited","year":"2560"},{"salary":"","faculty":"วิศวกรรมโยธา","company":"SGS (Thailand) Limited","year":"2561"},{"salary":"18000","faculty":"วิศวกรรมโยธา","company":"SGS (Thailand) Limited","year":"2562"},{"salary":"","faculty":"วิทยาการคอมพิวเตอร์","company":"Move Ahead Media Ltd.","year":"2559"},{"salary":"","faculty":"วิทยาการคอมพิวเตอร์","company":"Move Ahead Media Ltd.","year":"2560"},{"salary":"","faculty":"วิทยาการคอมพิวเตอร์","company":"Move Ahead Media Ltd.","year":"2561"},{"salary":"18000","faculty":"วิทยาการคอมพิวเตอร์","company":"Move Ahead Media Ltd.","year":"2562"},{"salary":"","faculty":"วิทยาการคอมพิวเตอร์","company":"V WISE IT CO., LTD./บจก. วี ไวซ์ ไอที","year":"2559"},{"salary":"","faculty":"วิทยาการคอมพิวเตอร์","company":"V WISE IT CO., LTD./บจก. วี ไวซ์ ไอที","year":"2560"},{"salary":"","faculty":"วิทยาการคอมพิวเตอร์","company":"V WISE IT CO., LTD./บจก. วี ไวซ์ ไอที","year":"2561"},{"salary":"18000","faculty":"วิทยาการคอมพิวเตอร์","company":"V WISE IT CO., LTD./บจก. วี ไวซ์ ไอที","year":"2562"},{"salary":"","faculty":"วิทยาการคอมพิวเตอร์","company":"Digio (Thailand) Co., Ltd.","year":"2559"},{"salary":"","faculty":"วิทยาการคอมพิวเตอร์","company":"Digio (Thailand) Co., Ltd.","year":"2560"},{"salary":"","faculty":"วิทยาการคอมพิวเตอร์","company":"Digio (Thailand) Co., Ltd.","year":"2561"},{"salary":"18000","faculty":"วิทยาการคอมพิวเตอร์","company":"Digio (Thailand) Co., Ltd.","year":"2562"},{"salary":"","faculty":"สถาปัตยกรรมภายใน","company":"Kanok Furniture & Decoration Co., Ltd.","year":"2559"},{"salary":"","faculty":"สถาปัตยกรรมภายใน","company":"Kanok Furniture & Decoration Co., Ltd.","year":"2560"},{"salary":"","faculty":"สถาปัตยกรรมภายใน","company":"Kanok Furniture & Decoration Co., Ltd.","year":"2561"},{"salary":"20000","faculty":"สถาปัตยกรรมภายใน","company":"Kanok Furniture & Decoration Co., Ltd.","year":"2562"},{"salary":"","faculty":"วิศวกรรมอาหาร","company":"Ajinomoto (Thailand) Co., Ltd.","year":"2559"},{"salary":"","faculty":"วิศวกรรมอาหาร","company":"Ajinomoto (Thailand) Co., Ltd.","year":"2560"},{"salary":"","faculty":"วิศวกรรมอาหาร","company":"Ajinomoto (Thailand) Co., Ltd.","year":"2561"},{"salary":"15000","faculty":"วิศวกรรมอาหาร","company":"Ajinomoto (Thailand) Co., Ltd.","year":"2562"},{"salary":"","faculty":"วิศวกรรมอุตสาหการ","company":"Benchmark Electronics (Thailand) Public Company Limited","year":"2559"},{"salary":"","faculty":"วิศวกรรมอุตสาหการ","company":"Benchmark Electronics (Thailand) Public Company Limited","year":"2560"},{"salary":"","faculty":"วิศวกรรมอุตสาหการ","company":"Benchmark Electronics (Thailand) Public Company Limited","year":"2561"},{"salary":"20000","faculty":"วิศวกรรมอุตสาหการ","company":"Benchmark Electronics (Thailand) Public Company Limited","year":"2562"},{"salary":"","faculty":"ศิลปศาสตร์ญี่ปุ่น","company":"RGF HR Agent Recruitment (Thailand) Co., Ltd.","year":"2559"},{"salary":"","faculty":"ศิลปศาสตร์ญี่ปุ่น","company":"RGF HR Agent Recruitment (Thailand) Co., Ltd.","year":"2560"},{"salary":"","faculty":"ศิลปศาสตร์ญี่ปุ่น","company":"RGF HR Agent Recruitment (Thailand) Co., Ltd.","year":"2561"},{"salary":"20000","faculty":"ศิลปศาสตร์ญี่ปุ่น","company":"RGF HR Agent Recruitment (Thailand) Co., Ltd.","year":"2562"},{"salary":"","faculty":"วิทยาการคอมพิวเตอร์","company":"Fischer & Partners Co., Ltd.","year":"2559"},{"salary":"","faculty":"วิทยาการคอมพิวเตอร์","company":"Fischer & Partners Co., Ltd.","year":"2560"},{"salary":"","faculty":"วิทยาการคอมพิวเตอร์","company":"Fischer & Partners Co., Ltd.","year":"2561"},{"salary":"20000","faculty":"วิทยาการคอมพิวเตอร์","company":"Fischer & Partners Co., Ltd.","year":"2562"},{"salary":"","faculty":"ศิลปศาสตร์อังกฤษ","company":"บริษัท มินเซนแมชีนเนอรี่ จำกัด","year":"2559"},{"salary":"","faculty":"ศิลปศาสตร์อังกฤษ","company":"บริษัท มินเซนแมชีนเนอรี่ จำกัด","year":"2560"},{"salary":"","faculty":"ศิลปศาสตร์อังกฤษ","company":"บริษัท มินเซนแมชีนเนอรี่ จำกัด","year":"2561"},{"salary":"15000","faculty":"ศิลปศาสตร์อังกฤษ","company":"บริษัท มินเซนแมชีนเนอรี่ จำกัด","year":"2562"},{"salary":"","faculty":"สถาปัตยกรรมภายใน","company":"บริษัท มินเซนแมชีนเนอรี่ จำกัด","year":"2559"},{"salary":"","faculty":"สถาปัตยกรรมภายใน","company":"บริษัท มินเซนแมชีนเนอรี่ จำกัด","year":"2560"},{"salary":"","faculty":"สถาปัตยกรรมภายใน","company":"บริษัท มินเซนแมชีนเนอรี่ จำกัด","year":"2561"},{"salary":"15000","faculty":"สถาปัตยกรรมภายใน","company":"บริษัท มินเซนแมชีนเนอรี่ จำกัด","year":"2562"},{"salary":"","faculty":"แพทยศาสตร์","company":"บริษัท เมดีซ กรุ๊ป จำกัด","year":"2559"},{"salary":"","faculty":"แพทยศาสตร์","company":"บริษัท เมดีซ กรุ๊ป จำกัด","year":"2560"},{"salary":"","faculty":"แพทยศาสตร์","company":"บริษัท เมดีซ กรุ๊ป จำกัด","year":"2561"},{"salary":"15000","faculty":"แพทยศาสตร์","company":"บริษัท เมดีซ กรุ๊ป จำกัด","year":"2562"},{"salary":"","faculty":"วิศวกรรมโยธา","company":"บริษัท โปรเจค แพลนนิ่ง เซอร์วิส จำกัด (มหาชน)","year":"2559"},{"salary":"","faculty":"วิศวกรรมโยธา","company":"บริษัท โปรเจค แพลนนิ่ง เซอร์วิส จำกัด (มหาชน)","year":"2560"},{"salary":"","faculty":"วิศวกรรมโยธา","company":"บริษัท โปรเจค แพลนนิ่ง เซอร์วิส จำกัด (มหาชน)","year":"2561"},{"salary":"18000","faculty":"วิศวกรรมโยธา","company":"บริษัท โปรเจค แพลนนิ่ง เซอร์วิส จำกัด (มหาชน)","year":"2562"},{"salary":"","faculty":"วิทยาการคอมพิวเตอร์","company":"บริษัท เอจีซี ไมโคร กลาส (ประเทศไทย) จำกัด","year":"2559"},{"salary":"","faculty":"วิทยาการคอมพิวเตอร์","company":"บริษัท เอจีซี ไมโคร กลาส (ประเทศไทย) จำกัด","year":"2560"},{"salary":"","faculty":"วิทยาการคอมพิวเตอร์","company":"บริษัท เอจีซี ไมโคร กลาส (ประเทศไทย) จำกัด","year":"2561"},{"salary":"18000","faculty":"วิทยาการคอมพิวเตอร์","company":"บริษัท เอจีซี ไมโคร กลาส (ประเทศไทย) จำกัด","year":"2562"},{"salary":"","faculty":"วิศวกรรมไฟฟ้า","company":"บริษัท พรีเมียร์ บิสสิเนส อินเตอร์ จำกัด","year":"2559"},{"salary":"","faculty":"วิศวกรรมไฟฟ้า","company":"บริษัท พรีเมียร์ บิสสิเนส อินเตอร์ จำกัด","year":"2560"},{"salary":"","faculty":"วิศวกรรมไฟฟ้า","company":"บริษัท พรีเมียร์ บิสสิเนส อินเตอร์ จำกัด","year":"2561"},{"salary":"20000","faculty":"วิศวกรรมไฟฟ้า","company":"บริษัท พรีเมียร์ บิสสิเนส อินเตอร์ จำกัด","year":"2562"},{"salary":"","faculty":"วิศวกรรมโยธา","company":"บริษัท พรีเมียร์ บิสสิเนส อินเตอร์ จำกัด","year":"2559"},{"salary":"","faculty":"วิศวกรรมโยธา","company":"บริษัท พรีเมียร์ บิสสิเนส อินเตอร์ จำกัด","year":"2560"},{"salary":"","faculty":"วิศวกรรมโยธา","company":"บริษัท พรีเมียร์ บิสสิเนส อินเตอร์ จำกัด","year":"2561"},{"salary":"20000","faculty":"วิศวกรรมโยธา","company":"บริษัท พรีเมียร์ บิสสิเนส อินเตอร์ จำกัด","year":"2562"},{"salary":"","faculty":"วิทยาการคอมพิวเตอร์","company":"คณะแพทยศาสตร์ศิริราชพยาบาล","year":"2559"},{"salary":"","faculty":"วิทยาการคอมพิวเตอร์","company":"คณะแพทยศาสตร์ศิริราชพยาบาล","year":"2560"},{"salary":"","faculty":"วิทยาการคอมพิวเตอร์","company":"คณะแพทยศาสตร์ศิริราชพยาบาล","year":"2561"},{"salary":"18000","faculty":"วิทยาการคอมพิวเตอร์","company":"คณะแพทยศาสตร์ศิริราชพยาบาล","year":"2562"},{"salary":"","faculty":"ศิลปศาสตร์อังกฤษ","company":"บริษัท แอดวานซ์ คอนแท็คเซ็นเตอร์ จำกัด","year":"2559"},{"salary":"","faculty":"ศิลปศาสตร์อังกฤษ","company":"บริษัท แอดวานซ์ คอนแท็คเซ็นเตอร์ จำกัด","year":"2560"},{"salary":"","faculty":"ศิลปศาสตร์อังกฤษ","company":"บริษัท แอดวานซ์ คอนแท็คเซ็นเตอร์ จำกัด","year":"2561"},{"salary":"18000","faculty":"ศิลปศาสตร์อังกฤษ","company":"บริษัท แอดวานซ์ คอนแท็คเซ็นเตอร์ จำกัด","year":"2562"},{"salary":"","faculty":"วิทยาการคอมพิวเตอร์","company":"บริษัท อิเลคทรอนิคส์ เอ็กซ์ตรีม จำกัด","year":"2559"},{"salary":"","faculty":"วิทยาการคอมพิวเตอร์","company":"บริษัท อิเลคทรอนิคส์ เอ็กซ์ตรีม จำกัด","year":"2560"},{"salary":"","faculty":"วิทยาการคอมพิวเตอร์","company":"บริษัท อิเลคทรอนิคส์ เอ็กซ์ตรีม จำกัด","year":"2561"},{"salary":"18000","faculty":"วิทยาการคอมพิวเตอร์","company":"บริษัท อิเลคทรอนิคส์ เอ็กซ์ตรีม จำกัด","year":"2562"},{"salary":"","faculty":"เทคโนโลยีสารสนเทศ","company":"บริษัท อิเลคทรอนิคส์ เอ็กซ์ตรีม จำกัด","year":"2559"},{"salary":"","faculty":"เทคโนโลยีสารสนเทศ","company":"บริษัท อิเลคทรอนิคส์ เอ็กซ์ตรีม จำกัด","year":"2560"},{"salary":"","faculty":"เทคโนโลยีสารสนเทศ","company":"บริษัท อิเลคทรอนิคส์ เอ็กซ์ตรีม จำกัด","year":"2561"},{"salary":"18000","faculty":"เทคโนโลยีสารสนเทศ","company":"บริษัท อิเลคทรอนิคส์ เอ็กซ์ตรีม จำกัด","year":"2562"},{"salary":"","faculty":"สถาปัตยกรรมภายใน","company":"บริษัท ออคโทพุส มีเดีย โซลูชันส์ จำกัด","year":"2559"},{"salary":"","faculty":"สถาปัตยกรรมภายใน","company":"บริษัท ออคโทพุส มีเดีย โซลูชันส์ จำกัด","year":"2560"},{"salary":"","faculty":"สถาปัตยกรรมภายใน","company":"บริษัท ออคโทพุส มีเดีย โซลูชันส์ จำกัด","year":"2561"},{"salary":"15000","faculty":"สถาปัตยกรรมภายใน","company":"บริษัท ออคโทพุส มีเดีย โซลูชันส์ จำกัด","year":"2562"},{"salary":"","faculty":"การบริหารจัดการ","company":"บริษัท โกไฟว์ จำกัด","year":"2559"},{"salary":"","faculty":"การบริหารจัดการ","company":"บริษัท โกไฟว์ จำกัด","year":"2560"},{"salary":"","faculty":"การบริหารจัดการ","company":"บริษัท โกไฟว์ จำกัด","year":"2561"},{"salary":"15000","faculty":"การบริหารจัดการ","company":"บริษัท โกไฟว์ จำกัด","year":"2562"},{"salary":"","faculty":"วิทยาการคอมพิวเตอร์","company":"บริษัท วีวิลแอพ จำกัด","year":"2559"},{"salary":"","faculty":"วิทยาการคอมพิวเตอร์","company":"บริษัท วีวิลแอพ จำกัด","year":"2560"},{"salary":"","faculty":"วิทยาการคอมพิวเตอร์","company":"บริษัท วีวิลแอพ จำกัด","year":"2561"},{"salary":"30000","faculty":"วิทยาการคอมพิวเตอร์","company":"บริษัท วีวิลแอพ จำกัด","year":"2562"},{"salary":"","faculty":"เทคโนโลยีสารสนเทศ","company":"บริษัท วีวิลแอพ จำกัด","year":"2559"},{"salary":"","faculty":"เทคโนโลยีสารสนเทศ","company":"บริษัท วีวิลแอพ จำกัด","year":"2560"},{"salary":"","faculty":"เทคโนโลยีสารสนเทศ","company":"บริษัท วีวิลแอพ จำกัด","year":"2561"},{"salary":"30000","faculty":"เทคโนโลยีสารสนเทศ","company":"บริษัท วีวิลแอพ จำกัด","year":"2562"},{"salary":"","faculty":"วิศวกรรมไฟฟ้า","company":"บริษัท แม็กซ์เครน แมชชีนเนอรี่ จำกัด","year":"2559"},{"salary":"","faculty":"วิศวกรรมไฟฟ้า","company":"บริษัท แม็กซ์เครน แมชชีนเนอรี่ จำกัด","year":"2560"},{"salary":"","faculty":"วิศวกรรมไฟฟ้า","company":"บริษัท แม็กซ์เครน แมชชีนเนอรี่ จำกัด","year":"2561"},{"salary":"40000","faculty":"วิศวกรรมไฟฟ้า","company":"บริษัท แม็กซ์เครน แมชชีนเนอรี่ จำกัด","year":"2562"},{"salary":"","faculty":"วิศวกรรมเครื่องกล","company":"บริษัท แม็กซ์เครน แมชชีนเนอรี่ จำกัด","year":"2559"},{"salary":"","faculty":"วิศวกรรมเครื่องกล","company":"บริษัท แม็กซ์เครน แมชชีนเนอรี่ จำกัด","year":"2560"},{"salary":"","faculty":"วิศวกรรมเครื่องกล","company":"บริษัท แม็กซ์เครน แมชชีนเนอรี่ จำกัด","year":"2561"},{"salary":"40000","faculty":"วิศวกรรมเครื่องกล","company":"บริษัท แม็กซ์เครน แมชชีนเนอรี่ จำกัด","year":"2562"},{"salary":"","faculty":"วิทยาศาตร์","company":"บริษัท โบนันซ่าเทค จำกัด","year":"2559"},{"salary":"","faculty":"วิทยาศาตร์","company":"บริษัท โบนันซ่าเทค จำกัด","year":"2560"},{"salary":"","faculty":"วิทยาศาตร์","company":"บริษัท โบนันซ่าเทค จำกัด","year":"2561"},{"salary":"20000","faculty":"วิทยาศาตร์","company":"บริษัท โบนันซ่าเทค จำกัด","year":"2562"},{"salary":"","faculty":"วิศวกรรมอาหาร","company":"บริษัท โบนันซ่าเทค จำกัด","year":"2559"},{"salary":"","faculty":"วิศวกรรมอาหาร","company":"บริษัท โบนันซ่าเทค จำกัด","year":"2560"},{"salary":"","faculty":"วิศวกรรมอาหาร","company":"บริษัท โบนันซ่าเทค จำกัด","year":"2561"},{"salary":"20000","faculty":"วิศวกรรมอาหาร","company":"บริษัท โบนันซ่าเทค จำกัด","year":"2562"},{"salary":"","faculty":"การบริหารจัดการ","company":"บริษัท จัดหางาน กู๊ด จ๊อบ โปรเพสชัลแนล (ประเทศไทย) จำกัด","year":"2559"},{"salary":"","faculty":"การบริหารจัดการ","company":"บริษัท จัดหางาน กู๊ด จ๊อบ โปรเพสชัลแนล (ประเทศไทย) จำกัด","year":"2560"},{"salary":"","faculty":"การบริหารจัดการ","company":"บริษัท จัดหางาน กู๊ด จ๊อบ โปรเพสชัลแนล (ประเทศไทย) จำกัด","year":"2561"},{"salary":"20000","faculty":"การบริหารจัดการ","company":"บริษัท จัดหางาน กู๊ด จ๊อบ โปรเพสชัลแนล (ประเทศไทย) จำกัด","year":"2562"},{"salary":"","faculty":"วิทยาศาสตร์เทคโนโลยีชีวภาพ","company":"บริษัท ไทย อะโกร เอ็นเนอร์ยี่ จำกัด (มหาชน)","year":"2559"},{"salary":"","faculty":"วิทยาศาสตร์เทคโนโลยีชีวภาพ","company":"บริษัท ไทย อะโกร เอ็นเนอร์ยี่ จำกัด (มหาชน)","year":"2560"},{"salary":"","faculty":"วิทยาศาสตร์เทคโนโลยีชีวภาพ","company":"บริษัท ไทย อะโกร เอ็นเนอร์ยี่ จำกัด (มหาชน)","year":"2561"},{"salary":"18000","faculty":"วิทยาศาสตร์เทคโนโลยีชีวภาพ","company":"บริษัท ไทย อะโกร เอ็นเนอร์ยี่ จำกัด (มหาชน)","year":"2562"},{"salary":"","faculty":"วิทยาศาตร์เคมีสิ่งแวดล้อม","company":"บริษัท ไทย อะโกร เอ็นเนอร์ยี่ จำกัด (มหาชน)","year":"2559"},{"salary":"","faculty":"วิทยาศาตร์เคมีสิ่งแวดล้อม","company":"บริษัท ไทย อะโกร เอ็นเนอร์ยี่ จำกัด (มหาชน)","year":"2560"},{"salary":"","faculty":"วิทยาศาตร์เคมีสิ่งแวดล้อม","company":"บริษัท ไทย อะโกร เอ็นเนอร์ยี่ จำกัด (มหาชน)","year":"2561"},{"salary":"18000","faculty":"วิทยาศาตร์เคมีสิ่งแวดล้อม","company":"บริษัท ไทย อะโกร เอ็นเนอร์ยี่ จำกัด (มหาชน)","year":"2562"},{"salary":"","faculty":"วิศวกรรมเคมีอุตสาหกรรม","company":"บริษัท ไทย อะโกร เอ็นเนอร์ยี่ จำกัด (มหาชน)","year":"2559"},{"salary":"","faculty":"วิศวกรรมเคมีอุตสาหกรรม","company":"บริษัท ไทย อะโกร เอ็นเนอร์ยี่ จำกัด (มหาชน)","year":"2560"},{"salary":"","faculty":"วิศวกรรมเคมีอุตสาหกรรม","company":"บริษัท ไทย อะโกร เอ็นเนอร์ยี่ จำกัด (มหาชน)","year":"2561"},{"salary":"18000","faculty":"วิศวกรรมเคมีอุตสาหกรรม","company":"บริษัท ไทย อะโกร เอ็นเนอร์ยี่ จำกัด (มหาชน)","year":"2562"},{"salary":"","faculty":"วิศวกรรมเคมี","company":"บริษัท ไทย อะโกร เอ็นเนอร์ยี่ จำกัด (มหาชน)","year":"2559"},{"salary":"","faculty":"วิศวกรรมเคมี","company":"บริษัท ไทย อะโกร เอ็นเนอร์ยี่ จำกัด (มหาชน)","year":"2560"},{"salary":"","faculty":"วิศวกรรมเคมี","company":"บริษัท ไทย อะโกร เอ็นเนอร์ยี่ จำกัด (มหาชน)","year":"2561"},{"salary":"20000","faculty":"วิศวกรรมเคมี","company":"บริษัท ไทย อะโกร เอ็นเนอร์ยี่ จำกัด (มหาชน)","year":"2562"},{"salary":"","faculty":"การบริหารจัดการ","company":"บริษัท หาดทิพย์ จำกัด (มหาชน) สงขลา","year":"2559"},{"salary":"","faculty":"การบริหารจัดการ","company":"บริษัท หาดทิพย์ จำกัด (มหาชน) สงขลา","year":"2560"},{"salary":"","faculty":"การบริหารจัดการ","company":"บริษัท หาดทิพย์ จำกัด (มหาชน) สงขลา","year":"2561"},{"salary":"18000","faculty":"การบริหารจัดการ","company":"บริษัท หาดทิพย์ จำกัด (มหาชน) สงขลา","year":"2562"},{"salary":"","faculty":"ศิลปศาสตร์อังกฤษ","company":"บริษัท กรุงเทพประกันชีวิต จำกัด (มหาชน)","year":"2559"},{"salary":"","faculty":"ศิลปศาสตร์อังกฤษ","company":"บริษัท กรุงเทพประกันชีวิต จำกัด (มหาชน)","year":"2560"},{"salary":"","faculty":"ศิลปศาสตร์อังกฤษ","company":"บริษัท กรุงเทพประกันชีวิต จำกัด (มหาชน)","year":"2561"},{"salary":"20000","faculty":"ศิลปศาสตร์อังกฤษ","company":"บริษัท กรุงเทพประกันชีวิต จำกัด (มหาชน)","year":"2562"},{"salary":"","faculty":"วิศวกรรมเครื่องกล","company":"บริษัท แคนนอน ปราจีนบุรี (ประเทศไทย) จำกัด","year":"2559"},{"salary":"","faculty":"วิศวกรรมเครื่องกล","company":"บริษัท แคนนอน ปราจีนบุรี (ประเทศไทย) จำกัด","year":"2560"},{"salary":"","faculty":"วิศวกรรมเครื่องกล","company":"บริษัท แคนนอน ปราจีนบุรี (ประเทศไทย) จำกัด","year":"2561"},{"salary":"20000","faculty":"วิศวกรรมเครื่องกล","company":"บริษัท แคนนอน ปราจีนบุรี (ประเทศไทย) จำกัด","year":"2562"},{"salary":"","faculty":"วิศวกรรมโยธา","company":"บริษัท เอนเนอร์ยี่ คอมเพล็กซ์ จำกัด","year":"2559"},{"salary":"","faculty":"วิศวกรรมโยธา","company":"บริษัท เอนเนอร์ยี่ คอมเพล็กซ์ จำกัด","year":"2560"},{"salary":"","faculty":"วิศวกรรมโยธา","company":"บริษัท เอนเนอร์ยี่ คอมเพล็กซ์ จำกัด","year":"2561"},{"salary":"20000","faculty":"วิศวกรรมโยธา","company":"บริษัท เอนเนอร์ยี่ คอมเพล็กซ์ จำกัด","year":"2562"},{"salary":"","faculty":"วิศวกรรมเคมี","company":"บริษัท เป็นเอก ควอลิตี้ออยล์ จำกัด","year":"2559"},{"salary":"","faculty":"วิศวกรรมเคมี","company":"บริษัท เป็นเอก ควอลิตี้ออยล์ จำกัด","year":"2560"},{"salary":"","faculty":"วิศวกรรมเคมี","company":"บริษัท เป็นเอก ควอลิตี้ออยล์ จำกัด","year":"2561"},{"salary":"20000","faculty":"วิศวกรรมเคมี","company":"บริษัท เป็นเอก ควอลิตี้ออยล์ จำกัด","year":"2562"},{"salary":"","faculty":"การบริหารจัดการ","company":"Krungsiam Beverage Co.,Ltd","year":"2559"},{"salary":"","faculty":"การบริหารจัดการ","company":"Krungsiam Beverage Co.,Ltd","year":"2560"},{"salary":"","faculty":"การบริหารจัดการ","company":"Krungsiam Beverage Co.,Ltd","year":"2561"},{"salary":"15000","faculty":"การบริหารจัดการ","company":"Krungsiam Beverage Co.,Ltd","year":"2562"},{"salary":"","faculty":"การบริหารจัดการ","company":"บริษัท ชาญอิสสระ ดีเวล็อปเมนท์ จำกัด (มหาชน)","year":"2559"},{"salary":"","faculty":"การบริหารจัดการ","company":"บริษัท ชาญอิสสระ ดีเวล็อปเมนท์ จำกัด (มหาชน)","year":"2560"},{"salary":"","faculty":"การบริหารจัดการ","company":"บริษัท ชาญอิสสระ ดีเวล็อปเมนท์ จำกัด (มหาชน)","year":"2561"},{"salary":"15000","faculty":"การบริหารจัดการ","company":"บริษัท ชาญอิสสระ ดีเวล็อปเมนท์ จำกัด (มหาชน)","year":"2562"},{"salary":"","faculty":"การบริหารจัดการ","company":"บริษัท ณวรางค์ แอสเซท จำกัด","year":"2559"},{"salary":"","faculty":"การบริหารจัดการ","company":"บริษัท ณวรางค์ แอสเซท จำกัด","year":"2560"},{"salary":"","faculty":"การบริหารจัดการ","company":"บริษัท ณวรางค์ แอสเซท จำกัด","year":"2561"},{"salary":"30000","faculty":"การบริหารจัดการ","company":"บริษัท ณวรางค์ แอสเซท จำกัด","year":"2562"},{"salary":"","faculty":"วิทยาการคอมพิวเตอร์","company":"บริษัท เน็ตก้า ซิสเต็ม จำกัด","year":"2559"},{"salary":"","faculty":"วิทยาการคอมพิวเตอร์","company":"บริษัท เน็ตก้า ซิสเต็ม จำกัด","year":"2560"},{"salary":"","faculty":"วิทยาการคอมพิวเตอร์","company":"บริษัท เน็ตก้า ซิสเต็ม จำกัด","year":"2561"},{"salary":"20000","faculty":"วิทยาการคอมพิวเตอร์","company":"บริษัท เน็ตก้า ซิสเต็ม จำกัด","year":"2562"},{"salary":"","faculty":"วิทยาการคอมพิวเตอร์","company":"บริษัท ดับบลิวทีซี คอมพิวเตอร์ จำกัด","year":"2559"},{"salary":"","faculty":"วิทยาการคอมพิวเตอร์","company":"บริษัท ดับบลิวทีซี คอมพิวเตอร์ จำกัด","year":"2560"},{"salary":"","faculty":"วิทยาการคอมพิวเตอร์","company":"บริษัท ดับบลิวทีซี คอมพิวเตอร์ จำกัด","year":"2561"},{"salary":"20000","faculty":"วิทยาการคอมพิวเตอร์","company":"บริษัท ดับบลิวทีซี คอมพิวเตอร์ จำกัด","year":"2562"},{"salary":"","faculty":"เทคโนโลยีสารสนเทศ","company":"บริษัท ดับบลิวทีซี คอมพิวเตอร์ จำกัด","year":"2559"},{"salary":"","faculty":"เทคโนโลยีสารสนเทศ","company":"บริษัท ดับบลิวทีซี คอมพิวเตอร์ จำกัด","year":"2560"},{"salary":"","faculty":"เทคโนโลยีสารสนเทศ","company":"บริษัท ดับบลิวทีซี คอมพิวเตอร์ จำกัด","year":"2561"},{"salary":"20000","faculty":"เทคโนโลยีสารสนเทศ","company":"บริษัท ดับบลิวทีซี คอมพิวเตอร์ จำกัด","year":"2562"},{"salary":"","faculty":"วิศวกรรมคอมพิวเตอร์","company":"บริษัท ดับบลิวทีซี คอมพิวเตอร์ จำกัด","year":"2559"},{"salary":"","faculty":"วิศวกรรมคอมพิวเตอร์","company":"บริษัท ดับบลิวทีซี คอมพิวเตอร์ จำกัด","year":"2560"},{"salary":"","faculty":"วิศวกรรมคอมพิวเตอร์","company":"บริษัท ดับบลิวทีซี คอมพิวเตอร์ จำกัด","year":"2561"},{"salary":"20000","faculty":"วิศวกรรมคอมพิวเตอร์","company":"บริษัท ดับบลิวทีซี คอมพิวเตอร์ จำกัด","year":"2562"},{"salary":"","faculty":"วิทยาการคอมพิวเตอร์","company":"บริษัท พรีไซซ คอร์ปอเรชั่น จำกัด (มหาชน)","year":"2559"},{"salary":"","faculty":"วิทยาการคอมพิวเตอร์","company":"บริษัท พรีไซซ คอร์ปอเรชั่น จำกัด (มหาชน)","year":"2560"},{"salary":"","faculty":"วิทยาการคอมพิวเตอร์","company":"บริษัท พรีไซซ คอร์ปอเรชั่น จำกัด (มหาชน)","year":"2561"},{"salary":"19000","faculty":"วิทยาการคอมพิวเตอร์","company":"บริษัท พรีไซซ คอร์ปอเรชั่น จำกัด (มหาชน)","year":"2562"},{"salary":"","faculty":"เทคโนโลยีสารสนเทศ","company":"บริษัท พรีไซซ คอร์ปอเรชั่น จำกัด (มหาชน)","year":"2559"},{"salary":"","faculty":"เทคโนโลยีสารสนเทศ","company":"บริษัท พรีไซซ คอร์ปอเรชั่น จำกัด (มหาชน)","year":"2560"},{"salary":"","faculty":"เทคโนโลยีสารสนเทศ","company":"บริษัท พรีไซซ คอร์ปอเรชั่น จำกัด (มหาชน)","year":"2561"},{"salary":"19000","faculty":"เทคโนโลยีสารสนเทศ","company":"บริษัท พรีไซซ คอร์ปอเรชั่น จำกัด (มหาชน)","year":"2562"},{"salary":"","faculty":"วิศวกรรมคอมพิวเตอร์","company":"บริษัท พรีไซซ คอร์ปอเรชั่น จำกัด (มหาชน)","year":"2559"},{"salary":"","faculty":"วิศวกรรมคอมพิวเตอร์","company":"บริษัท พรีไซซ คอร์ปอเรชั่น จำกัด (มหาชน)","year":"2560"},{"salary":"","faculty":"วิศวกรรมคอมพิวเตอร์","company":"บริษัท พรีไซซ คอร์ปอเรชั่น จำกัด (มหาชน)","year":"2561"},{"salary":"19000","faculty":"วิศวกรรมคอมพิวเตอร์","company":"บริษัท พรีไซซ คอร์ปอเรชั่น จำกัด (มหาชน)","year":"2562"},{"salary":"","faculty":"วิศวกรรมไฟฟ้า","company":"บริษัท ถิรไทย จำกัด (มหาชน)","year":"2559"},{"salary":"","faculty":"วิศวกรรมไฟฟ้า","company":"บริษัท ถิรไทย จำกัด (มหาชน)","year":"2560"},{"salary":"","faculty":"วิศวกรรมไฟฟ้า","company":"บริษัท ถิรไทย จำกัด (มหาชน)","year":"2561"},{"salary":"20000","faculty":"วิศวกรรมไฟฟ้า","company":"บริษัท ถิรไทย จำกัด (มหาชน)","year":"2562"},{"salary":"","faculty":"วิศวกรรมอาหาร","company":"บริษัท ฟู้ดอินโนเวชั่นแอนด์เดเวลอปเม้นท์ จำกัด","year":"2559"},{"salary":"","faculty":"วิศวกรรมอาหาร","company":"บริษัท ฟู้ดอินโนเวชั่นแอนด์เดเวลอปเม้นท์ จำกัด","year":"2560"},{"salary":"","faculty":"วิศวกรรมอาหาร","company":"บริษัท ฟู้ดอินโนเวชั่นแอนด์เดเวลอปเม้นท์ จำกัด","year":"2561"},{"salary":"20000","faculty":"วิศวกรรมอาหาร","company":"บริษัท ฟู้ดอินโนเวชั่นแอนด์เดเวลอปเม้นท์ จำกัด","year":"2562"},{"salary":"","faculty":"วิศวกรรมเครื่องกล","company":"บริษัท ฟู้ดอินโนเวชั่นแอนด์เดเวลอปเม้นท์ จำกัด","year":"2559"},{"salary":"","faculty":"วิศวกรรมเครื่องกล","company":"บริษัท ฟู้ดอินโนเวชั่นแอนด์เดเวลอปเม้นท์ จำกัด","year":"2560"},{"salary":"","faculty":"วิศวกรรมเครื่องกล","company":"บริษัท ฟู้ดอินโนเวชั่นแอนด์เดเวลอปเม้นท์ จำกัด","year":"2561"},{"salary":"20000","faculty":"วิศวกรรมเครื่องกล","company":"บริษัท ฟู้ดอินโนเวชั่นแอนด์เดเวลอปเม้นท์ จำกัด","year":"2562"},{"salary":"","faculty":"วิศวกรรมเครื่องกล","company":"บริษัท อีเอ็มซี จำกัด (มหาชน)","year":"2559"},{"salary":"","faculty":"วิศวกรรมเครื่องกล","company":"บริษัท อีเอ็มซี จำกัด (มหาชน)","year":"2560"},{"salary":"","faculty":"วิศวกรรมเครื่องกล","company":"บริษัท อีเอ็มซี จำกัด (มหาชน)","year":"2561"},{"salary":"20000","faculty":"วิศวกรรมเครื่องกล","company":"บริษัท อีเอ็มซี จำกัด (มหาชน)","year":"2562"},{"salary":"","faculty":"การบริหารจัดการ","company":"Bangkok Bank Public Company Limited/ธนาคารกรุงเทพ จำกัด (มหาชน)","year":"2559"},{"salary":"","faculty":"การบริหารจัดการ","company":"Bangkok Bank Public Company Limited/ธนาคารกรุงเทพ จำกัด (มหาชน)","year":"2560"},{"salary":"","faculty":"การบริหารจัดการ","company":"Bangkok Bank Public Company Limited/ธนาคารกรุงเทพ จำกัด (มหาชน)","year":"2561"},{"salary":"20000","faculty":"การบริหารจัดการ","company":"Bangkok Bank Public Company Limited/ธนาคารกรุงเทพ จำกัด (มหาชน)","year":"2562"},{"salary":"","faculty":"การบริหารจัดการ","company":"The Klinique Medical Clinic Public Company Limited","year":"2559"},{"salary":"","faculty":"การบริหารจัดการ","company":"The Klinique Medical Clinic Public Company Limited","year":"2560"},{"salary":"","faculty":"การบริหารจัดการ","company":"The Klinique Medical Clinic Public Company Limited","year":"2561"},{"salary":"22000","faculty":"การบริหารจัดการ","company":"The Klinique Medical Clinic Public Company Limited","year":"2562"},{"salary":"","faculty":"วิศวกรรมไฟฟ้า","company":"การไฟฟ้านครหลวง(กฟน.)","year":"2559"},{"salary":"","faculty":"วิศวกรรมไฟฟ้า","company":"การไฟฟ้านครหลวง(กฟน.)","year":"2560"},{"salary":"","faculty":"วิศวกรรมไฟฟ้า","company":"การไฟฟ้านครหลวง(กฟน.)","year":"2561"},{"salary":"21500","faculty":"วิศวกรรมไฟฟ้า","company":"การไฟฟ้านครหลวง(กฟน.)","year":"2562"},{"salary":"","faculty":"วิทยาศาสตร์เคมี","company":"กรมทรัพยากรธรณี","year":"2559"},{"salary":"","faculty":"วิทยาศาสตร์เคมี","company":"กรมทรัพยากรธรณี","year":"2560"},{"salary":"","faculty":"วิทยาศาสตร์เคมี","company":"กรมทรัพยากรธรณี","year":"2561"},{"salary":"16000","faculty":"วิทยาศาสตร์เคมี","company":"กรมทรัพยากรธรณี","year":"2562"},{"salary":"","faculty":"เกษตรศาสตร์","company":"กรมส่งเสริมการเกษตร","year":"2559"},{"salary":"","faculty":"เกษตรศาสตร์","company":"กรมส่งเสริมการเกษตร","year":"2560"},{"salary":"","faculty":"เกษตรศาสตร์","company":"กรมส่งเสริมการเกษตร","year":"2561"},{"salary":"15000","faculty":"เกษตรศาสตร์","company":"กรมส่งเสริมการเกษตร","year":"2562"},{"salary":"","faculty":"วิทยาศาสตร์ฟิสิกส์","company":"กรมอุตุนิยมวิทยา","year":"2559"},{"salary":"","faculty":"วิทยาศาสตร์ฟิสิกส์","company":"กรมอุตุนิยมวิทยา","year":"2560"},{"salary":"","faculty":"วิทยาศาสตร์ฟิสิกส์","company":"กรมอุตุนิยมวิทยา","year":"2561"},{"salary":"16000","faculty":"วิทยาศาสตร์ฟิสิกส์","company":"กรมอุตุนิยมวิทยา","year":"2562"},{"salary":"","faculty":"ศิลปศาสตร์จีน","company":"Delta Electronics (Thailand)","year":"2559"},{"salary":"","faculty":"ศิลปศาสตร์จีน","company":"Delta Electronics (Thailand)","year":"2560"},{"salary":"","faculty":"ศิลปศาสตร์จีน","company":"Delta Electronics (Thailand)","year":"2561"},{"salary":"15000","faculty":"ศิลปศาสตร์จีน","company":"Delta Electronics (Thailand)","year":"2562"}]